qqhrz/__init__.py
qqhrz/ztorch.py
qqhrz-0.5.dist-info/LICENSE
qqhrz-0.5.dist-info/METADATA
qqhrz-0.5.dist-info/WHEEL
qqhrz-0.5.dist-info/top_level.txt
qqhrz-0.5.dist-info/RECORD
