Metadata-Version: 2.1
Name: qqhrz
Version: 0.5
Summary: 动手学深度学习pytorch版，代码实现。
Author-email: zkj <zhkaij@foxmail.com>
Project-URL: Homepage, https://github.com/pypa/sampleproject
Project-URL: Bug Tracker, https://github.com/pypa/sampleproject/issues
Classifier: Programming Language :: Python :: 3
Classifier: License :: OSI Approved :: MIT License
Classifier: Operating System :: OS Independent
Requires-Python: >=3.8
License-File: LICENSE
